dikshantlock/__init__.py
dikshantlock/generator.py
dikshantlock-1.0.0.dist-info/licenses/LICENSE.txt
dikshantlock-1.0.0.dist-info/METADATA
dikshantlock-1.0.0.dist-info/WHEEL
dikshantlock-1.0.0.dist-info/top_level.txt
dikshantlock-1.0.0.dist-info/RECORD
