Metadata-Version: 2.4
Name: dikshantlock
Version: 1.0.0
Summary: Secure password generation toolkit
Author-email: Dikshant Ghimire <dikkughimire@gmail.com>
Project-URL: Homepage, https://github.com/dikshantgh/dikshantlock
Classifier: Programming Language :: Python :: 3
Classifier: License :: OSI Approved :: MIT License
Classifier: Operating System :: OS Independent
Requires-Python: >=3.7
License-File: LICENSE.txt
Dynamic: license-file
